Metadata-Version: 2.4
Name: minha-biblioteca-sppal
Version: 0.1.0
Summary: Uma biblioteca de exemplo em Python
Author-email: Teu Nome <teu@email.com>
License: MIT
Requires-Python: >=3.8
License-File: license
Dynamic: license-file
